[
    {
        "Name": "Performance",
        "Travelers":[
            {
                "File": ["img/seasons/Performance/Frantic_Stagehand/Traveler.png"],
                "Name": "Frantic_Stagehand"
            },
            {
                "File": ["img/seasons/Performance/Forgetful_Storyteller/Traveler.png"],
                "Name": "Forgetful_Storyteller"
            },
            {
                "File": ["img/seasons/Performance/Mellow_Musician/Traveler.png"],
                "Name": "Mellow_Musician"
            },
            {
                "File": ["img/seasons/Performance/Modest_Dancer/Traveler.png"],
                "Name": "Modest_Dancer"
            }
        ]    
    },
    {
        "Name": "Abyss",
        "Travelers":[
            {
                "File": ["img/seasons/Abyss/Anxious_Angler/Traveler.png"],
                "Name": "Anxious_Angler"
            }
            ,
            {
                "File": ["img/seasons/Abyss/Ceasing_Commodore/Traveler.png"],
                "Name": "Ceasing_Commodore"
            },
            {
                "File": ["img/seasons/Abyss/Bumbling_Boatswain/Traveler.png"],
                "Name": "Bumbling_Boatswain"
            },
            {
                "File": ["img/seasons/Abyss/Cackling_Cannoneer/Traveler.png"],
                "Name": "Cackling_Cannoneer"
            }
        ]
        
    },
    {
        "Name": "Flight",
        "Travelers":[
            {
                "File": ["img/seasons/Flight/Flight_Guide/Traveler.png"],
                "Name": "Flight_Guide"
            },
            {
                "File": ["img/seasons/Flight/Lively_Navigator/Traveler.png"],
                "Name": "Lively_Navigator"
            },
            {
                "File": ["img/seasons/Flight/Light_Whisperer/Traveler.png"],
                "Name": "Light_Whisperer"
            },
            {
                "File": ["img/seasons/Flight/Tinkering_Chimesmith/Traveler.png"],
                "Name": "Tinkering_Chimesmith"
            },
            {
                "File": ["img/seasons/Flight/Talented_Builder/Traveler.png"],
                "Name": "Talented_Builder"
            }
        ]
        
    },
    {
        "Name": "The_Little_Prince",
        "Travelers":[
            {
                "File": ["img/seasons/The_Little_Prince/Beckoning_Ruler/Traveler.png"],
                "Name": "Beckoning_Ruler"
            },
            {
                "File": ["img/seasons/The_Little_Prince/Gloating_Narcissist/Traveler.png"],
                "Name": "Gloating_Narcissist"
            },
            {
                "File": ["img/seasons/The_Little_Prince/Stretching_Lamplighter/Traveler.png"],
                "Name": "Stretching_Lamplighter"
            },
            {
                "File": ["img/seasons/The_Little_Prince/Slouching_Soldier/Traveler.png"],
                "Name": "Slouching_Soldier"
            },
            {
                "File": ["img/seasons/The_Little_Prince/Sneezing_Geographer/Traveler.png"],
                "Name": "Sneezing_Geographer"
            },
            {
                "File": ["img/seasons/The_Little_Prince/Star_Collector/Traveler.png"],
                "Name": "Star_Collector"
            }
        ]
        
    },
    {
        "Name": "Assembly",
        "Travelers":[
            {
                "File": ["img/seasons/Assembly/Assembly_Guide/Traveler.png"],
                "Name": "Assembly_Guide"        
            },
            {
                "File": ["img/seasons/Assembly/Baffled_Botanist/Traveler.png"],
                "Name": "Baffled_Botanist"
            },
            {
                "File": ["img/seasons/Assembly/Scolding_Student/Traveler.png"],
                "Name": "Scolding_Student"
            },
            {
                "File": ["img/seasons/Assembly/Scaredy_Cadet/Traveler.png"],
                "Name": "Scaredy_Cadet"
            },
            {
                "File": ["img/seasons/Assembly/Marching_Adventurer/Traveler.png"],
                "Name": "Marching_Adventurer"
            },
            {
                "File": ["img/seasons/Assembly/Chuckling_Scout/Traveler.png"],
                "Name": "Chuckling_Scout"
            },
            {
                "File": ["img/seasons/Assembly/Daydream_Forester/Traveler.png"],
                "Name": "Daydream_Forester"
            }
        ]
        
    },
    {
        "Name": "Dreams",
        "Travelers":[
            {
                "File": ["img/seasons/Dreams/Bearhug_Hermit/Traveler.png"],
                "Name": "Bearhug_Hermit"
            },
            {
                "File": ["img/seasons/Dreams/Dancing_Performer/Traveler.png"],
                "Name": "Dancing_Performer"
            },
            {
                "File": ["img/seasons/Dreams/Peeking_Postman/Traveler.png"],
                "Name": "Peeking_Postman"
            },
            {
                "File": ["img/seasons/Dreams/Spinning_Mentor/Traveler.png"],
                "Name": "Spinning_Mentor"
            }
        ]
        
    },
    {
        "Name": "Prophecy",
        "Travelers":[
            {
                "File": ["img/seasons/Prophecy/Prophet_of_Water/Traveler.png"],
                "Name": "Prophet_of_Water"
            },
            {
                "File": ["img/seasons/Prophecy/Prophet_of_Earth/Traveler.png"],
                "Name": "Prophet_of_Earth"
            },
            {
                "File": ["img/seasons/Prophecy/Prophet_of_Air/Traveler.png"],
                "Name": "Prophet_of_Air"
            },
            {
                "File": ["img/seasons/Prophecy/Prophet_of_Fire/Traveler.png"],
                "Name": "Prophet_of_Fire"
            }
        ]
    },
    {
        "Name": "Santuary",
        "Travelers":[
            {
                "File": ["img/seasons/Santuary/Timid_Bookworm/Traveler.png"],
                "Name": "Timid_Bookworm"
            },
            {
                "File": ["img/seasons/Santuary/Rallying_Thrillseeker/Traveler.png"],
                "Name": "Rallying_Thrillseeker"
            },
            {
                "File": ["img/seasons/Santuary/Hiking_Grouch/Traveler.png"],
                "Name": "Hiking_Grouch"
            },
            {
                "File": ["img/seasons/Santuary/Grateful_Shell_Collector/Traveler.png"],
                "Name": "Grateful_Shell_Collector"
            },
            {
                "File": ["img/seasons/Santuary/Chill_Sunbather/Traveler.png"],
                "Name": "Chill_Sunbather"
            },
            {
                "File": ["img/seasons/Santuary/Jelly_Whisperer/Traveler.png"],
                "Name": "Jelly_Whisperer"
            }
        ]
    },
    {
        "Name": "Enchantment",
        "Travelers":[
            {
                "File": ["img/seasons/Enchantment/Nodding_Muralist/Traveler.png"],
                "Name": "Nodding_Muralist"
            },
            {
                "File": ["img/seasons/Enchantment/Indifferent_Alchemist/Traveler.png"],
                "Name": "Indifferent_Alchemist"
            },
            {
                "File": ["img/seasons/Enchantment/Crab_Walker/Traveler.png"],
                "Name": "Crab_Walker"
            },
            {
                "File": ["img/seasons/Enchantment/Scarecrow_Farmer/Traveler.png"],
                "Name": "Scarecrow_Farmer"
            },
            {
                "File": ["img/seasons/Enchantment/Snoozing_Carpenter/Traveler.png"],
                "Name": "Snoozing_Carpenter"
            },
            {
                "File": ["img/seasons/Enchantment/Playfighting_Herbalist/Traveler.png"],
                "Name": "Playfighting_Herbalist"
            }
        ]
    },
    {
        "Name": "Rhythm",
        "Travelers":[
            {
                "File": ["img/seasons/Rhythm/Troupe_Greeter/Traveler.png"],
                "Name": "Troupe_Greeter"
            },
            {
                "File": ["img/seasons/Rhythm/Festival_Spin_Dancer/Traveler.png"],
                "Name": "Festival_Spin_Dancer"
            },
            {
                "File": ["img/seasons/Rhythm/Admiring_Actor/Traveler.png"],
                "Name": "Admiring_Actor"
            },
            {
                "File": ["img/seasons/Rhythm/Troupe_Juggler/Traveler.png"],
                "Name": "Troupe_Juggler"
            },
            {
                "File": ["img/seasons/Rhythm/Respectful_Pianist/Traveler.png"],
                "Name": "Respectful_Pianist"
            },
            {
                "File": ["img/seasons/Rhythm/Thoughtful_Director/Traveler.png"],
                "Name": "Thoughtful_Director"
            }
        ]
    },
    {
        "Name": "Belonging",
        "Travelers":[
            {
                "File": ["img/seasons/Belonging/Confetti_Cousin/Traveler.png"],
                "Name": "Confetti_Cousin"
            },
            {
                "File": ["img/seasons/Belonging/Boogie_Kid/Traveler.png"],
                "Name": "Boogie_Kid"
            },
            {
                "File": ["img/seasons/Belonging/Sparkler_Parent/Traveler.png"],
                "Name": "Sparkler_Parent"
            },
            {
                "File": ["img/seasons/Belonging/Wise_Grandparent/Traveler.png"],
                "Name": "Wise_Grandparent"
            },
            {
                "File": ["img/seasons/Belonging/Pleaful_Parent/Traveler.png"],
                "Name": "Pleaful_Parent"
            },
            {
                "File": ["img/seasons/Belonging/Hairtousle_Teen/Traveler.png"],
                "Name": "Hairtousle_Teen"
            }
        ]
    },
    {
        "Name": "Lightseekers",
        "Travelers":[
            {
                "File": ["img/seasons/Lightseekers/Piggyback_Lightseeker/Traveler.png"],
                "Name": "Piggyback_Lightseeker"
            },
            {
                "File": ["img/seasons/Lightseekers/Doublefive_Light_Catcher/Traveler.png"],
                "Name": "Doublefive_Light_Catcher"
            },
            {
                "File": ["img/seasons/Lightseekers/Laidback_Pioneer/Traveler.png"],
                "Name": "Laidback_Pioneer"
            },
            {
                "File": ["img/seasons/Lightseekers/Twirling_Champion/Traveler.png"],
                "Name": "Twirling_Champion"
            },
            {
                "File": ["img/seasons/Lightseekers/Crab_Whisperer/Traveler.png"],
                "Name": "Crab_Whisperer"
            },
            {
                "File": ["img/seasons/Lightseekers/Shushing_Light_Scholar/Traveler.png"],
                "Name": "Shushing_Light_Scholar"
            }
        ]
    },
    {
        "Name": "Gratitude",
        "Travelers":[
            {
                "File": ["img/seasons/Gratitude/Sassy_Drifter/Traveler.png"],
                "Name": "Sassy_Drifter"
            },
            {
                "File": ["img/seasons/Gratitude/Stretching_Guru/Traveler.png"],
                "Name": "Stretching_Guru"
            },
            {
                "File": ["img/seasons/Gratitude/Leaping_Dancer/Traveler.png"],
                "Name": "Leaping_Dancer"
            },
            {
                "File": ["img/seasons/Gratitude/Greeting_Shaman/Traveler.png"],
                "Name": "Greeting_Shaman"
            },
            {
                "File": ["img/seasons/Gratitude/Saluting_Protector/Traveler.png"],
                "Name": "Saluting_Protector"
            }
        ]
    }
]
